mpwebui/__init__.py
mpwebui/caller.py
mpwebui/mpapi.py
mpapi_webui-0.0.1.dist-info/METADATA
mpapi_webui-0.0.1.dist-info/WHEEL
mpapi_webui-0.0.1.dist-info/top_level.txt
mpapi_webui-0.0.1.dist-info/RECORD
