Metadata-Version: 2.1
Name: mpapi-webui
Version: 0.0.1
Summary: Multi Processing SD WebUI API Caller
Author: HotMoistone
Author-email: lex.les38@gmail.com
